simple_sanitizer/__init__.py
simple_sanitizer/cli.py
simple_sanitizer/maskers.py
simple_sanitizer-0.1.2.dist-info/licenses/LICENSE
tests/__init__.py
tests/test_maskers.py
simple_sanitizer-0.1.2.dist-info/METADATA
simple_sanitizer-0.1.2.dist-info/WHEEL
simple_sanitizer-0.1.2.dist-info/entry_points.txt
simple_sanitizer-0.1.2.dist-info/top_level.txt
simple_sanitizer-0.1.2.dist-info/RECORD
