Metadata-Version: 2.4
Name: simple-sanitizer
Version: 0.1.2
Classifier: Programming Language :: Python :: 3
Classifier: Programming Language :: Python :: 3.8
Classifier: Programming Language :: Python :: 3.9
Classifier: Programming Language :: Python :: 3.10
Classifier: Programming Language :: Python :: 3.11
Classifier: License :: OSI Approved :: MIT License
Classifier: Operating System :: OS Independent
Requires-Python: >=3.12
License-File: LICENSE
Provides-Extra: dev
Requires-Dist: pytest>=9.0.2; extra == "dev"
Requires-Dist: ruff>=0.14.10; extra == "dev"
Dynamic: classifier
Dynamic: license-file
Dynamic: provides-extra
Dynamic: requires-python
